atomic_save/__init__.py
atomic_save/test.py
atomic_save-0.0.0.dist-info/METADATA
atomic_save-0.0.0.dist-info/WHEEL
atomic_save-0.0.0.dist-info/top_level.txt
atomic_save-0.0.0.dist-info/RECORD
